AUTHORS.txt
CHANGELOG.txt
LICENSE.txt
README.txt
development.ini
setup.cfg
setup.py
bin/econ-admin
bin/econ-test
data/954e44ca-e1ce-11db-9f8d-00145101c316/data.csv
data/954e44ca-e1ce-11db-9f8d-00145101c316/metadata.txt
data/9d72cc30-df7f-11db-bac7-00145101c316/data.csv
data/9d72cc30-df7f-11db-bac7-00145101c316/metadata.txt
data/copyright_registrations_us/data.csv
data/copyright_registrations_us/metadata.txt
data/music_sales/data.csv
data/music_sales/metadata.txt
data/uk_interest_rates/convert.py
data/uk_interest_rates/data.csv
data/uk_interest_rates/data.original.csv
data/uk_interest_rates/metadata.txt
data/uk_price_index_1850-2002_annual/data.csv
data/uk_price_index_1850-2002_annual/metadata.txt
data/world_population_historical/consolidate.py
data/world_population_historical/data.csv
data/world_population_historical/metadata.txt
econ/CopyrightModel.py
econ/CopyrightModelTest.py
econ/DemandFunction.py
econ/DemandFunctionTest.py
econ/DiscountRate.py
econ/DiscountRateTest.py
econ/NetworkEffectsModel.py
econ/NetworkEffectsModelTest.py
econ/Producer.py
econ/ProducerTest.py
econ/__init__.py
econ/data_test.py
econ/log.py
econ/logtest.py
econ/plot_help.py
econ.egg-info/PKG-INFO
econ.egg-info/SOURCES.txt
econ.egg-info/dependency_links.txt
econ.egg-info/entry_points.txt
econ.egg-info/requires.txt
econ.egg-info/top_level.txt
econ/data/__init__.py
econ/data/tabular.py
econ/data/tabular_test.py
econ/store/__init__.py
econ/store/bundle.py
econ/store/bundle_test.py
econ/test/__init__.py
econ/www/__init__.py
econ/www/websetup.py
econ/www/config/__init__.py
econ/www/config/environment.py
econ/www/config/middleware.py
econ/www/config/routing.py
econ/www/controllers/__init__.py
econ/www/controllers/error.py
econ/www/controllers/root.py
econ/www/controllers/template.py
econ/www/i18n/__init__.py
econ/www/lib/__init__.py
econ/www/lib/app_globals.py
econ/www/lib/base.py
econ/www/lib/helpers.py
econ/www/models/__init__.py
econ/www/templates/__init__.py
econ/www/templates/current_value.html
econ/www/templates/index.html
econ/www/templates/layout.html
econ/www/templates/store_index.html
econ/www/templates/view_html.html
econ/www/tests/__init__.py
