Metadata-Version: 1.0
Name: econ
Version: 0.4
Summary: An open set of economics related tools, data and services.
Home-page: http://www.knowledgeforge.net/project/econ/
Author: Rufus Pollock
Author-email: rufus@rufuspollock.org
License: GPL
Platform: UNKNOWN
